raps/__init__.py
raps/__init__.pyi
raps/raps.abi3.so
raps_bindings-4.3.0.dist-info/METADATA
raps_bindings-4.3.0.dist-info/WHEEL
raps_bindings-4.3.0.dist-info/RECORD
