Metadata-Version: 2.4
Name: raps-bindings
Version: 4.3.0
Classifier: Development Status :: 4 - Beta
Classifier: Intended Audience :: Developers
Classifier: License :: OSI Approved :: Apache Software License
Classifier: Operating System :: OS Independent
Classifier: Programming Language :: Python :: 3
Classifier: Programming Language :: Python :: 3.8
Classifier: Programming Language :: Python :: 3.9
Classifier: Programming Language :: Python :: 3.10
Classifier: Programming Language :: Python :: 3.11
Classifier: Programming Language :: Python :: 3.12
Classifier: Programming Language :: Python :: 3.13
Classifier: Programming Language :: Rust
Classifier: Topic :: Software Development :: Libraries :: Python Modules
Requires-Dist: pytest>=7.0 ; extra == 'dev'
Requires-Dist: pytest-asyncio>=0.21 ; extra == 'dev'
Provides-Extra: dev
Summary: Python bindings for RAPS - programmatic access to Autodesk Platform Services
Keywords: autodesk,aps,forge,cad,bim,python,api
Author: Dmytro Yemelianov
License: Apache-2.0
Requires-Python: >=3.8
Project-URL: Changelog, https://github.com/dmytro-yemelianov/raps/blob/main/CHANGELOG.md
Project-URL: Documentation, https://rapscli.xyz/docs
Project-URL: Homepage, https://rapscli.xyz
Project-URL: Repository, https://github.com/dmytro-yemelianov/raps
